{"doors": [{"assetId": "Doorway_Double_8", "id": "door|2|3", "openable": true, "openness": 1, "room0": "room|2", "room1": "room|3", "wall0": "wall|2|0.00|3.45|3.45|3.45", "wall1": "wall|3|0.00|3.45|3.45|3.45", "holePolygon": [{"x": 0.24539375146398754, "y": 0, "z": 0}, {"x": 2.210540650687315, "y": 2.099397659301758, "z": 0}], "assetPosition": {"x": 1.22614265353898, "y": 1.049698829650879, "z": 0}}, {"assetId": "Doorway_5", "id": "door|1|3", "openable": false, "openness": 0, "room0": "room|3", "room1": "room|3", "wall0": "wall|3|5.18|5.18|5.18|6.90", "wall1": "wall|exterior|5.18|5.18|5.18|6.90", "holePolygon": [{"x": 0.5144455822842965, "y": 0, "z": 0}, {"x": 1.5519841107266794, "y": 2.0979503514245152, "z": 0}], "assetPosition": {"x": 1.0318954669597398, "y": 1.0459483740851283, "z": 0}}], "metadata": {"agent": {"horizon": 30, "position": {"x": 1.75, "y": 0.95, "z": 5.5}, "rotation": {"x": 0, "y": 0, "z": 0}, "standing": true}, "roomSpecId": "bedroom-bathroom", "schema": "1.0.0", "warnings": {}, "agentPoses": {"arm": {"horizon": 30, "position": {"x": 1.75, "y": 0.95, "z": 5.5}, "rotation": {"x": 0, "y": 0, "z": 0}, "standing": true}, "default": {"horizon": 30, "position": {"x": 1.75, "y": 0.95, "z": 5.5}, "rotation": {"x": 0, "y": 0, "z": 0}, "standing": true}, "locobot": {"horizon": 30, "position": {"x": 1.75, "y": 0.95, "z": 5.5}, "rotation": {"x": 0, "y": 0, "z": 0}}, "stretch": {"horizon": 30, "position": {"x": 1.75, "y": 0.95, "z": 5.5}, "rotation": {"x": 0, "y": 0, "z": 0}, "standing": true}}}, "objects": [{"assetId": "Bed_5", "children": [{"assetId": "pillow_12", "id": "Pillow|2|0|1", "kinematic": false, "position": {"x": 6.493993864536286, "y": 0.9111773669719696, "z": 0.563642883300782}, "rotation": {"x": 0, "y": 270.0, "z": 0}, "layer": "Procedural2"}, {"assetId": "Remote_3", "id": "RemoteControl|surface|2|11", "kinematic": false, "position": {"x": 5.433651924133301, "y": 0.7901095151901245, "z": 0.6891776323318481}, "rotation": {"x": 0.0, "y": 270.0, "z": 0.0}, "layer": "Procedural2"}], "id": "Bed|2|0|0", "isDirty": false, "kinematic": true, "position": {"x": 5.707624652862549, "y": 0.4218328893184662, "z": 0.5636428833007819}, "rotation": {"x": 0, "y": 270.0, "z": 0}, "layer": "Procedural2", "material": null}, {"assetId": "Dresser_413_1", "children": [{"assetId": "CreditCard_1", "id": "CreditCard|surface|2|0", "kinematic": false, "position": {"x": 0.22195059061050415, "y": 1.1617507934570312, "z": 0.22319209575653076}, "rotation": {"x": -0.0, "y": 90.0, "z": -0.0}, "layer": "Procedural2"}, {"assetId": "Pen_1", "id": "Pen|surface|2|5", "kinematic": false, "position": {"x": 0.09351478517055511, "y": 0.8793848752975464, "z": 0.3378925919532776}, "rotation": {"x": -0.0, "y": 180.0, "z": -0.0}, "layer": "Procedural2"}, {"assetId": "Remote_2", "id": "RemoteControl|surface|2|9", "kinematic": false, "position": {"x": 0.060532912611961365, "y": 1.1714603900909424, "z": 0.22319208085536957}, "rotation": {"x": -0.0, "y": 180.0, "z": -0.0}, "layer": "Procedural2"}, {"assetId": "Remote_2", "id": "RemoteControl|surface|2|10", "kinematic": false, "position": {"x": 0.21223504841327667, "y": 0.6254977583885193, "z": 0.48904478549957275}, "rotation": {"x": -0.0, "y": 180.0, "z": -0.0}, "layer": "Procedural2"}], "id": "Dresser|2|1", "kinematic": true, "position": {"x": 0.1575717270374298, "y": 0.5758355855941772, "z": 0.41706045866012575}, "rotation": {"x": 0, "y": 90, "z": 0}, "layer": "Procedural2", "material": null}, {"assetId": "TV_Stand_206_1", "children": [{"assetId": "Television_27", "id": "Television|2|2|1", "kinematic": true, "position": {"x": 0.3267582893371582, "y": 1.3574086427688599, "z": 2.0451236718376364}, "rotation": {"x": 0, "y": 90.0, "z": 0}, "layer": "Procedural2"}, {"assetId": "RoboTHOR_book_ai2_2_v", "id": "Book|surface|2|2", "kinematic": false, "position": {"x": 0.4750640392303467, "y": 0.7724906206130981, "z": 1.5947942733764648}, "rotation": {"x": -0.0, "y": 180.0, "z": -0.0}, "layer": "Procedural2"}, {"assetId": "Tissue_Box_1", "id": "TissueBox|surface|2|3", "kinematic": false, "position": {"x": 0.5337724089622498, "y": 0.5490624904632568, "z": 2.3598294258117676}, "rotation": {"x": -0.0, "y": 90.0, "z": -0.0}, "layer": "Procedural2"}], "id": "TVStand|2|2|0", "kinematic": true, "position": {"x": 0.3267582893371582, "y": 0.37626194953918457, "z": 2.0451236718376364}, "rotation": {"x": 0, "y": 90.0, "z": 0}, "layer": "Procedural2", "material": null}, {"assetId": "Armchair_222_1", "id": "ArmChair|2|3|0", "kinematic": true, "position": {"x": 5.571935418396671, "y": 0.47257378697395325, "z": 2.939443482875824}, "rotation": {"x": 0, "y": 180.0, "z": 0}, "layer": "Procedural2", "material": null}, {"assetId": "Floor_Lamp_4", "id": "FloorLamp|2|3|1", "isOn": true, "kinematic": false, "position": {"x": 6.6049143892673055, "y": 0.9341566562652588, "z": 2.939443482875824}, "rotation": {"x": 0, "y": 197.99152885205066, "z": 0}, "layer": "Procedural2", "material": null}, {"assetId": "Dining_Table_201_1", "children": [{"assetId": "RoboTHOR_baseball_bat_rawlings_v", "id": "BaseballBat|surface|2|1", "kinematic": false, "position": {"x": 3.6776299476623535, "y": 0.010770037770271301, "z": 0.5673424005508423}, "rotation": {"x": 295.7575378417969, "y": 87.37939453125, "z": 89.99948120117188}, "layer": "Procedural2"}, {"assetId": "RoboTHOR_remote_coolux_v", "id": "RemoteControl|surface|2|4", "kinematic": false, "position": {"x": 3.192315101623535, "y": 0.6935303211212158, "z": 1.3164100646972656}, "rotation": {"x": -0.0, "y": 0.0, "z": 0.0}, "layer": "Procedural2"}, {"assetId": "Houseplant_10", "id": "HousePlant|surface|2|6", "kinematic": false, "position": {"x": 1.8696401119232178, "y": 0.9361113905906677, "z": 1.1709104776382446}, "rotation": {"x": -0.0, "y": 0.0, "z": 0.0}, "layer": "Procedural2"}, {"assetId": "RoboTHOR_mug_ai2_1_v", "id": "Mug|surface|2|7", "kinematic": false, "position": {"x": 2.0664849281311035, "y": 0.7269535064697266, "z": 0.6984119415283203}, "rotation": {"x": -0.0, "y": 0.0, "z": 0.0}, "layer": "Procedural2"}, {"assetId": "CD_1", "id": "CD|surface|2|8", "kinematic": false, "position": {"x": 2.526552677154541, "y": 0.6863585114479065, "z": 1.3164101839065552}, "rotation": {"x": -0.0, "y": 0.0, "z": 0.0}, "layer": "Procedural2"}, {"assetId": "Stone_Statue_4", "color": {"b": 0.39680373357042886, "g": 0.2935697850902863, "r": 0.3294979528271884}, "id": "Statue|surface|2|12", "kinematic": false, "position": {"x": 2.5187058448791504, "y": 1.0274722456932068, "z": 0.5748122930526733}, "rotation": {"x": -0.0, "y": 0.0, "z": 0.0}, "layer": "Procedural2"}, {"assetId": "Bowl_27", "id": "Bowl|surface|2|13", "kinematic": false, "position": {"x": 2.9703946113586426, "y": 0.7784200191497803, "z": 1.0692108869552612}, "rotation": {"x": -0.0, "y": 0.0, "z": 0.0}, "layer": "Procedural2"}, {"assetId": "Book_28", "id": "Book|surface|2|14", "kinematic": false, "position": {"x": 2.3039727210998535, "y": 0.6994839906692505, "z": 0.6984121203422546}, "rotation": {"x": -0.0, "y": 0.0, "z": 0.0}, "layer": "Procedural2"}], "id": "DiningTable|2|4|0", "kinematic": true, "position": {"x": 2.5265533760064827, "y": 0.3391079604625702, "z": 0.9456108819797335}, "rotation": {"x": 0, "y": 0.0, "z": 0}, "layer": "Procedural2", "material": null}, {"assetId": "RoboTHOR_chair_antnas", "id": "Chair|2|4|1", "kinematic": true, "position": {"x": 2.5265533760064827, "y": 0.4125499725341797, "z": 0.35175898187902543}, "rotation": {"x": 0, "y": 344.9516107411302, "z": 0}, "layer": "Procedural2", "material": null}, {"assetId": "Toilet_2", "children": [{"assetId": "Spray_Bottle_7", "id": "SprayBottle|surface|3|15", "kinematic": false, "position": {"x": 0.3574625551700592, "y": 1.073786973953247, "z": 6.689866542816162}, "rotation": {"x": 0.0, "y": 269.9998474121094, "z": 0.0}, "layer": "Procedural1"}, {"assetId": "Toilet_Paper_Used_Up", "id": "ToiletPaper|surface|3|16", "kinematic": false, "position": {"x": 0.4863511323928833, "y": 1.0116610527038574, "z": 6.770241737365723}, "rotation": {"x": 0.0, "y": 269.9998474121094, "z": 0.0}, "layer": "Procedural1"}, {"assetId": "Candle_3", "id": "Candle|surface|3|17", "kinematic": false, "position": {"x": 0.36135122179985046, "y": 1.0131235122680664, "z": 6.7434492111206055}, "rotation": {"x": 0.0, "y": 269.9998474121094, "z": 0.0}, "layer": "Procedural1"}], "id": "Toilet|3|0", "kinematic": true, "position": {"x": 0.29485302567481997, "y": 0.472759485244751, "z": 6.4467952637672425}, "rotation": {"x": 0, "y": 180, "z": 0}, "layer": "Procedural1", "material": null}, {"assetId": "Sink_26", "children": [{"assetId": "Bathroom_Faucet_30", "id": "Faucet|3|1|1", "kinematic": true, "position": {"x": 3.3696561547020627, "y": 1.1324992626905441, "z": 6.742102194905281}, "rotation": {"x": 0, "y": 180.0, "z": 0}, "layer": "Procedural1"}], "id": "Sink|3|1|0", "kinematic": true, "position": {"x": 3.3696561547020627, "y": 0.4927992820739746, "z": 6.556828597068787}, "rotation": {"x": 0, "y": 180.0, "z": 0}, "layer": "Procedural1", "material": null}, {"assetId": "Plunger_2", "id": "Plunger|3|2", "kinematic": false, "position": {"x": 1.889017965627124, "y": 0.2696691155433655, "z": 6.803996780395508}, "rotation": {"x": 0, "y": 180, "z": 0}, "layer": "Procedural1", "material": null}, {"assetId": "bin_7", "id": "GarbageCan|3|3", "kinematic": false, "position": {"x": 4.320294629588866, "y": 0.27942752838134766, "z": 6.727832937121391}, "rotation": {"x": 0, "y": 180, "z": 0}, "layer": "Procedural1", "material": null}, {"assetId": "Wall_Decor_Photo_10", "id": "Painting|2|5", "kinematic": true, "position": {"x": 2.0355318823845763, "y": 1.7337192686091436, "z": 0.020870485454797746}, "rotation": {"x": 0, "y": 0, "z": 0}, "layer": "Procedural2", "material": null}, {"assetId": "Wall_Decor_Photo_9", "id": "Painting|2|6", "kinematic": true, "position": {"x": 3.4728704854547976, "y": 1.539637635011325, "z": 4.484649150389515}, "rotation": {"x": 0, "y": 90, "z": 0}, "layer": "Procedural2", "material": null}, {"assetId": "Wall_Decor_Photo_6", "id": "Painting|2|7", "kinematic": true, "position": {"x": 4.510649500919886, "y": 2.1219963669881317, "z": 0.020870485454797746}, "rotation": {"x": 0, "y": 0, "z": 0}, "layer": "Procedural2", "material": null}, {"assetId": "Wall_Decor_Painting_10", "id": "Painting|3|4", "kinematic": true, "position": {"x": 0.01299965113401413, "y": 1.6595425369511445, "z": 4.496163579015944}, "rotation": {"x": 0, "y": 90, "z": 0}, "layer": "Procedural1", "material": null}, {"assetId": "Wall_Decor_Painting_9", "id": "Painting|3|5", "kinematic": true, "position": {"x": 3.4374252756386996, "y": 1.589348476526384, "z": 4.656287473388748}, "rotation": {"x": 0, "y": 270, "z": 0}, "layer": "Procedural1", "material": null}], "proceduralParameters": {"ceilingMaterial": {"name": "RedBrick"}, "floorColliderThickness": 1.0, "lights": [{"id": "DirectionalLight", "indirectMultiplier": 1.0, "intensity": 1, "position": {"x": 0.84, "y": 0.1855, "z": -1.09}, "rgb": {"r": 1.0, "g": 1.0, "b": 1.0}, "rotation": {"x": 66, "y": 75, "z": 0}, "shadow": {"type": "Soft", "strength": 1, "normalBias": 0, "bias": 0, "nearPlane": 0.2, "resolution": "FromQualitySettings"}, "type": "directional"}, {"id": "light_2", "intensity": 0.45, "position": {"x": 3.547456798866855, "y": 2.819422069016421, "z": 2.01370370847283}, "range": 15, "rgb": {"r": 1.0, "g": 0.855, "b": 0.722}, "shadow": {"type": "Soft", "strength": 1, "normalBias": 0, "bias": 0.05, "nearPlane": 0.2, "resolution": "FromQualitySettings"}, "type": "point", "layer": "Procedural2", "cullingMaskOff": ["Procedural0", "Procedural1", "Procedural3"]}, {"id": "light_3", "intensity": 0.45, "position": {"x": 2.243679958270546, "y": 2.819422069016421, "z": 5.350059986090182}, "range": 15, "rgb": {"r": 1.0, "g": 0.855, "b": 0.722}, "shadow": {"type": "Soft", "strength": 1, "normalBias": 0, "bias": 0.05, "nearPlane": 0.2, "resolution": "FromQualitySettings"}, "type": "point", "layer": "Procedural1", "cullingMaskOff": ["Procedural0", "Procedural2", "Procedural3"]}], "receptacleHeight": 0.7, "reflections": [], "skyboxId": "SkyMountain"}, "rooms": [{"ceilings": [], "children": [], "floorMaterial": {"name": "LightWoodCounters2"}, "floorPolygon": [{"x": 0.0, "y": 0, "z": 0.0}, {"x": 0.0, "y": 0, "z": 3.452}, {"x": 3.452, "y": 0, "z": 3.452}, {"x": 3.452, "y": 0, "z": 5.178}, {"x": 5.178, "y": 0, "z": 5.178}, {"x": 5.178, "y": 0, "z": 3.452}, {"x": 6.903, "y": 0, "z": 3.452}, {"x": 6.903, "y": 0, "z": 0.0}], "id": "room|2", "roomType": "Bedroom", "layer": "Procedural2"}, {"ceilings": [], "children": [], "floorMaterial": {"name": "GreyFloor"}, "floorPolygon": [{"x": 0.0, "y": 0, "z": 3.452}, {"x": 0.0, "y": 0, "z": 6.903}, {"x": 5.178, "y": 0, "z": 6.903}, {"x": 5.178, "y": 0, "z": 5.178}, {"x": 3.452, "y": 0, "z": 5.178}, {"x": 3.452, "y": 0, "z": 3.452}], "id": "room|3", "roomType": "Bathroom", "layer": "Procedural1"}], "walls": [{"id": "wall|2|0.00|0.00|0.00|3.45", "material": {"name": "SubwayTilesRough 2"}, "polygon": [{"x": 0.0, "y": 0, "z": 0.0}, {"x": 0.0, "y": 0, "z": 3.452}, {"x": 0.0, "y": 3.019422069016421, "z": 0.0}, {"x": 0.0, "y": 3.019422069016421, "z": 3.452}], "roomId": "room|2", "layer": "Procedural2"}, {"id": "wall|2|0.00|3.45|3.45|3.45", "material": {"name": "SubwayTilesRough 2"}, "polygon": [{"x": 0.0, "y": 0, "z": 3.452}, {"x": 3.452, "y": 0, "z": 3.452}, {"x": 0.0, "y": 3.019422069016421, "z": 3.452}, {"x": 3.452, "y": 3.019422069016421, "z": 3.452}], "roomId": "room|2", "layer": "Procedural2"}, {"id": "wall|2|3.45|3.45|3.45|5.18", "material": {"name": "SubwayTilesRough 2"}, "polygon": [{"x": 3.452, "y": 0, "z": 3.452}, {"x": 3.452, "y": 0, "z": 5.178}, {"x": 3.452, "y": 3.019422069016421, "z": 3.452}, {"x": 3.452, "y": 3.019422069016421, "z": 5.178}], "roomId": "room|2", "layer": "Procedural2"}, {"id": "wall|2|3.45|5.18|5.18|5.18", "material": {"name": "SubwayTilesRough 2"}, "polygon": [{"x": 3.452, "y": 0, "z": 5.178}, {"x": 5.178, "y": 0, "z": 5.178}, {"x": 3.452, "y": 3.019422069016421, "z": 5.178}, {"x": 5.178, "y": 3.019422069016421, "z": 5.178}], "roomId": "room|2", "layer": "Procedural2"}, {"id": "wall|2|5.18|3.45|5.18|5.18", "material": {"name": "SubwayTilesRough 2"}, "polygon": [{"x": 5.178, "y": 0, "z": 5.178}, {"x": 5.178, "y": 0, "z": 3.452}, {"x": 5.178, "y": 3.019422069016421, "z": 5.178}, {"x": 5.178, "y": 3.019422069016421, "z": 3.452}], "roomId": "room|2", "layer": "Procedural2"}, {"id": "wall|2|5.18|3.45|6.90|3.45", "material": {"name": "SubwayTilesRough 2"}, "polygon": [{"x": 5.178, "y": 0, "z": 3.452}, {"x": 6.903, "y": 0, "z": 3.452}, {"x": 5.178, "y": 3.019422069016421, "z": 3.452}, {"x": 6.903, "y": 3.019422069016421, "z": 3.452}], "roomId": "room|2", "layer": "Procedural2"}, {"id": "wall|2|6.90|0.00|6.90|3.45", "material": {"name": "SubwayTilesRough 2"}, "polygon": [{"x": 6.903, "y": 0, "z": 3.452}, {"x": 6.903, "y": 0, "z": 0.0}, {"x": 6.903, "y": 3.019422069016421, "z": 3.452}, {"x": 6.903, "y": 3.019422069016421, "z": 0.0}], "roomId": "room|2", "layer": "Procedural2"}, {"id": "wall|2|0.00|0.00|6.90|0.00", "material": {"name": "SubwayTilesRough 2"}, "polygon": [{"x": 6.903, "y": 0, "z": 0.0}, {"x": 0.0, "y": 0, "z": 0.0}, {"x": 6.903, "y": 3.019422069016421, "z": 0.0}, {"x": 0.0, "y": 3.019422069016421, "z": 0.0}], "roomId": "room|2", "layer": "Procedural2"}, {"color": {"b": 0.5294117647058824, "g": 0.49019607843137253, "r": 0.0784313725490196}, "id": "wall|3|0.00|3.45|0.00|6.90", "material": {"name": "PureWhite", "color": {"b": 0.5294117647058824, "g": 0.49019607843137253, "r": 0.0784313725490196}}, "polygon": [{"x": 0.0, "y": 0, "z": 3.452}, {"x": 0.0, "y": 0, "z": 6.903}, {"x": 0.0, "y": 3.019422069016421, "z": 3.452}, {"x": 0.0, "y": 3.019422069016421, "z": 6.903}], "roomId": "room|3", "layer": "Procedural1"}, {"color": {"b": 0.5294117647058824, "g": 0.49019607843137253, "r": 0.0784313725490196}, "id": "wall|3|0.00|6.90|5.18|6.90", "material": {"name": "PureWhite", "color": {"b": 0.5294117647058824, "g": 0.49019607843137253, "r": 0.0784313725490196}}, "polygon": [{"x": 0.0, "y": 0, "z": 6.903}, {"x": 5.178, "y": 0, "z": 6.903}, {"x": 0.0, "y": 3.019422069016421, "z": 6.903}, {"x": 5.178, "y": 3.019422069016421, "z": 6.903}], "roomId": "room|3", "layer": "Procedural1"}, {"color": {"b": 0.5294117647058824, "g": 0.49019607843137253, "r": 0.0784313725490196}, "id": "wall|3|5.18|5.18|5.18|6.90", "material": {"name": "PureWhite", "color": {"b": 0.5294117647058824, "g": 0.49019607843137253, "r": 0.0784313725490196}}, "polygon": [{"x": 5.178, "y": 0, "z": 6.903}, {"x": 5.178, "y": 0, "z": 5.178}, {"x": 5.178, "y": 3.019422069016421, "z": 6.903}, {"x": 5.178, "y": 3.019422069016421, "z": 5.178}], "roomId": "room|3", "layer": "Procedural1"}, {"color": {"b": 0.5294117647058824, "g": 0.49019607843137253, "r": 0.0784313725490196}, "id": "wall|3|3.45|5.18|5.18|5.18", "material": {"name": "PureWhite", "color": {"b": 0.5294117647058824, "g": 0.49019607843137253, "r": 0.0784313725490196}}, "polygon": [{"x": 5.178, "y": 0, "z": 5.178}, {"x": 3.452, "y": 0, "z": 5.178}, {"x": 5.178, "y": 3.019422069016421, "z": 5.178}, {"x": 3.452, "y": 3.019422069016421, "z": 5.178}], "roomId": "room|3", "layer": "Procedural1"}, {"color": {"b": 0.5294117647058824, "g": 0.49019607843137253, "r": 0.0784313725490196}, "id": "wall|3|3.45|3.45|3.45|5.18", "material": {"name": "PureWhite", "color": {"b": 0.5294117647058824, "g": 0.49019607843137253, "r": 0.0784313725490196}}, "polygon": [{"x": 3.452, "y": 0, "z": 5.178}, {"x": 3.452, "y": 0, "z": 3.452}, {"x": 3.452, "y": 3.019422069016421, "z": 5.178}, {"x": 3.452, "y": 3.019422069016421, "z": 3.452}], "roomId": "room|3", "layer": "Procedural1"}, {"color": {"b": 0.5294117647058824, "g": 0.49019607843137253, "r": 0.0784313725490196}, "id": "wall|3|0.00|3.45|3.45|3.45", "material": {"name": "PureWhite", "color": {"b": 0.5294117647058824, "g": 0.49019607843137253, "r": 0.0784313725490196}}, "polygon": [{"x": 3.452, "y": 0, "z": 3.452}, {"x": 0.0, "y": 0, "z": 3.452}, {"x": 3.452, "y": 3.019422069016421, "z": 3.452}, {"x": 0.0, "y": 3.019422069016421, "z": 3.452}], "roomId": "room|3", "layer": "Procedural1"}, {"id": "wall|exterior|0.00|0.00|6.90|0.00", "material": {"name": "EggshellDrywall 1"}, "polygon": [{"x": 0.0, "y": 3.019422069016421, "z": 0.0}, {"x": 6.903, "y": 3.019422069016421, "z": 0.0}, {"x": 0.0, "y": 0, "z": 0.0}, {"x": 6.903, "y": 0, "z": 0.0}], "roomId": "exterior", "layer": "Procedural2"}, {"id": "wall|exterior|5.18|3.45|6.90|3.45", "material": {"name": "EggshellDrywall 1"}, "polygon": [{"x": 6.903, "y": 3.019422069016421, "z": 3.452}, {"x": 5.178, "y": 3.019422069016421, "z": 3.452}, {"x": 6.903, "y": 0, "z": 3.452}, {"x": 5.178, "y": 0, "z": 3.452}], "roomId": "exterior", "layer": "Procedural2"}, {"id": "wall|exterior|5.18|3.45|5.18|5.18", "material": {"name": "EggshellDrywall 1"}, "polygon": [{"x": 5.178, "y": 3.019422069016421, "z": 3.452}, {"x": 5.178, "y": 3.019422069016421, "z": 5.178}, {"x": 5.178, "y": 0, "z": 3.452}, {"x": 5.178, "y": 0, "z": 5.178}], "roomId": "exterior", "layer": "Procedural2"}, {"id": "wall|exterior|0.00|0.00|0.00|3.45", "material": {"name": "EggshellDrywall 1"}, "polygon": [{"x": 0.0, "y": 3.019422069016421, "z": 3.452}, {"x": 0.0, "y": 3.019422069016421, "z": 0.0}, {"x": 0.0, "y": 0, "z": 3.452}, {"x": 0.0, "y": 0, "z": 0.0}], "roomId": "exterior", "layer": "Procedural2"}, {"id": "wall|exterior|6.90|0.00|6.90|3.45", "material": {"name": "EggshellDrywall 1"}, "polygon": [{"x": 6.903, "y": 3.019422069016421, "z": 0.0}, {"x": 6.903, "y": 3.019422069016421, "z": 3.452}, {"x": 6.903, "y": 0, "z": 0.0}, {"x": 6.903, "y": 0, "z": 3.452}], "roomId": "exterior", "layer": "Procedural2"}, {"id": "wall|exterior|0.00|3.45|0.00|6.90", "material": {"name": "EggshellDrywall 1"}, "polygon": [{"x": 0.0, "y": 3.019422069016421, "z": 6.903}, {"x": 0.0, "y": 3.019422069016421, "z": 3.452}, {"x": 0.0, "y": 0, "z": 6.903}, {"x": 0.0, "y": 0, "z": 3.452}], "roomId": "exterior", "layer": "Procedural1"}, {"id": "wall|exterior|5.18|5.18|5.18|6.90", "material": {"name": "EggshellDrywall 1"}, "polygon": [{"x": 5.178, "y": 3.019422069016421, "z": 5.178}, {"x": 5.178, "y": 3.019422069016421, "z": 6.903}, {"x": 5.178, "y": 0, "z": 5.178}, {"x": 5.178, "y": 0, "z": 6.903}], "roomId": "exterior", "layer": "Procedural1"}, {"id": "wall|exterior|0.00|6.90|5.18|6.90", "material": {"name": "EggshellDrywall 1"}, "polygon": [{"x": 5.178, "y": 3.019422069016421, "z": 6.903}, {"x": 0.0, "y": 3.019422069016421, "z": 6.903}, {"x": 5.178, "y": 0, "z": 6.903}, {"x": 0.0, "y": 0, "z": 6.903}], "roomId": "exterior", "layer": "Procedural1"}], "windows": []}