{"doors": [{"assetId": "Doorway_4", "id": "door|2|6", "openable": true, "openness": 1, "room0": "room|2", "room1": "room|6", "wall0": "wall|2|0.00|3.71|3.71|3.71", "wall1": "wall|6|0.00|3.71|3.71|3.71", "holePolygon": [{"x": 0.7027771499535839, "y": 0, "z": 0}, {"x": 1.7453691985986035, "y": 2.103588104248047, "z": 0}], "assetPosition": {"x": 1.221921438217799, "y": 1.0517940521240234, "z": 0}}, {"assetId": "Doorway_10", "id": "door|1|6", "openable": false, "openness": 0, "room0": "room|6", "room1": "room|6", "wall0": "wall|6|0.00|11.14|1.86|11.14", "wall1": "wall|exterior|0.00|11.14|1.86|11.14", "holePolygon": [{"x": 0.3902069266258616, "y": 0, "z": 0}, {"x": 1.4314364130913158, "y": 2.103169581387192, "z": 0}], "assetPosition": {"x": 0.909155344714119, "y": 1.05002281954512, "z": 0}}], "metadata": {"agent": {"horizon": 30, "position": {"x": 2.25, "y": 0.95, "z": 8.25}, "rotation": {"x": 0, "y": 270, "z": 0}, "standing": true}, "roomSpecId": "kitchen-living-bedroom-room", "schema": "1.0.0", "warnings": {}, "agentPoses": {"arm": {"horizon": 30, "position": {"x": 2.25, "y": 0.95, "z": 8.25}, "rotation": {"x": 0, "y": 270, "z": 0}, "standing": true}, "default": {"horizon": 30, "position": {"x": 2.25, "y": 0.95, "z": 8.25}, "rotation": {"x": 0, "y": 270, "z": 0}, "standing": true}, "locobot": {"horizon": 30, "position": {"x": 2.25, "y": 0.95, "z": 8.25}, "rotation": {"x": 0, "y": 270, "z": 0}}, "stretch": {"horizon": 30, "position": {"x": 2.25, "y": 0.95, "z": 8.25}, "rotation": {"x": 0, "y": 270, "z": 0}, "standing": true}}}, "objects": [{"assetId": "Countertop_I_6x2", "children": [{"assetId": "Bowl_21", "id": "Bowl|surface|6|0", "kinematic": false, "position": {"x": 0.48929455876350403, "y": 0.9969772100448608, "z": 8.626788139343262}, "rotation": {"x": -0.0, "y": 90.0, "z": -0.0}, "layer": "Procedural1"}, {"assetId": "Houseplant_21", "id": "HousePlant|surface|6|1", "kinematic": false, "position": {"x": 0.37393900752067566, "y": 1.2788552045822144, "z": 9.091285705566406}, "rotation": {"x": -0.0, "y": 90.0, "z": -0.0}, "layer": "Procedural1"}, {"assetId": "Pen_3", "id": "Pen|surface|6|2", "kinematic": false, "position": {"x": 0.49445098638534546, "y": 0.9467101097106934, "z": 9.085136413574219}, "rotation": {"x": -0.0, "y": 90.0, "z": -0.0}, "layer": "Procedural1"}, {"assetId": "Pen_2", "id": "Pen|surface|6|3", "kinematic": false, "position": {"x": 0.4176904559135437, "y": 0.9481123685836792, "z": 10.00108814239502}, "rotation": {"x": -0.0, "y": 90.0, "z": -0.0}, "layer": "Procedural1"}, {"assetId": "Pepper_Shaker_1", "id": "PepperShaker|surface|6|4", "kinematic": false, "position": {"x": 0.18087315559387207, "y": 0.9981392621994019, "z": 9.771818161010742}, "rotation": {"x": -0.0, "y": 90.0, "z": -0.0}, "layer": "Procedural1"}, {"assetId": "Soap_Bottle_10", "id": "SoapBottle|surface|6|5", "kinematic": false, "position": {"x": 0.41121047735214233, "y": 1.0973296165466309, "z": 9.772100448608398}, "rotation": {"x": -0.0, "y": 90.0, "z": -0.0}, "layer": "Procedural1"}, {"assetId": "Potato_9", "id": "Potato|surface|6|6", "kinematic": false, "position": {"x": 0.33051952719688416, "y": 0.9813390970230103, "z": 8.63186264038086}, "rotation": {"x": -0.0, "y": 0.0, "z": 0.0}, "layer": "Procedural1"}, {"assetId": "Potato_18", "id": "Potato|surface|6|7", "kinematic": false, "position": {"x": 0.2610984444618225, "y": 0.979636549949646, "z": 8.856077194213867}, "rotation": {"x": -0.0, "y": 90.0, "z": -0.0}, "layer": "Procedural1"}, {"assetId": "Potato_20", "id": "Potato|surface|6|8", "kinematic": false, "position": {"x": 0.10368016362190247, "y": 0.9765017032623291, "z": 10.001564025878906}, "rotation": {"x": -0.0, "y": 90.0, "z": -0.0}, "layer": "Procedural1"}, {"assetId": "Fork_1", "id": "Fork|surface|6|9", "kinematic": false, "position": {"x": 0.5647315979003906, "y": 0.9518489837646484, "z": 10.023297309875488}, "rotation": {"x": -0.0, "y": 180.0, "z": -0.0}, "layer": "Procedural1"}, {"assetId": "Fork_1", "id": "Fork|surface|6|10", "kinematic": false, "position": {"x": 0.2576889991760254, "y": 0.9518489837646484, "z": 9.794309616088867}, "rotation": {"x": -0.0, "y": 180.0, "z": -0.0}, "layer": "Procedural1"}, {"assetId": "Mug_2", "id": "Mug|surface|6|15", "kinematic": false, "position": {"x": 0.4878210127353668, "y": 1.0442840337753296, "z": 8.871612548828125}, "rotation": {"x": -0.0, "y": 90.0, "z": -0.0}, "layer": "Procedural1"}, {"assetId": "ButterKnife_1", "id": "ButterKnife|surface|6|16", "kinematic": false, "position": {"x": 0.4136525094509125, "y": 0.9516711235046387, "z": 9.541111946105957}, "rotation": {"x": -0.0, "y": 90.0, "z": -0.0}, "layer": "Procedural1"}, {"assetId": "Dish_Sponge_1", "id": "DishSponge|surface|6|17", "kinematic": false, "position": {"x": 0.10416758060455322, "y": 0.9538848400115967, "z": 8.62716007232666}, "rotation": {"x": -0.0, "y": 90.0, "z": -0.0}, "layer": "Procedural1"}], "id": "CounterTop|6|0", "kinematic": true, "position": {"x": 0.33027570843696596, "y": 0.46873313188552856, "z": 9.313478073850288}, "rotation": {"x": 0, "y": 90, "z": 0}, "layer": "Procedural1", "material": null}, {"assetId": "Fridge_2", "children": [{"assetId": "Apple_20", "id": "Apple|surface|6|11", "kinematic": false, "position": {"x": 2.9984142780303955, "y": 1.419922947883606, "z": 4.088741779327393}, "rotation": {"x": -0.0, "y": 0.0, "z": 0.0}, "layer": "Procedural1"}, {"assetId": "Egg_11", "id": "Egg|surface|6|12", "kinematic": false, "position": {"x": 2.825355052947998, "y": 0.8646487474441529, "z": 4.088841438293457}, "rotation": {"x": -0.0, "y": 0.0, "z": 0.0}, "layer": "Procedural1"}, {"assetId": "Egg_5", "id": "Egg|surface|6|13", "kinematic": false, "position": {"x": 2.825355052947998, "y": 0.6108015656471253, "z": 4.201345920562744}, "rotation": {"x": -0.0, "y": 0.0, "z": 0.0}, "layer": "Procedural1"}, {"assetId": "Egg_21", "id": "Egg|surface|6|14", "kinematic": false, "position": {"x": 3.0849435329437256, "y": 1.0430437207221985, "z": 3.8988401889801025}, "rotation": {"x": -0.0, "y": 0.0, "z": 0.0}, "layer": "Procedural1"}], "id": "Fridge|6|1", "kinematic": true, "position": {"x": 2.824278676661568, "y": 0.9092216491699219, "z": 4.097966082334518}, "rotation": {"x": 0, "y": 0, "z": 0}, "layer": "Procedural1", "material": null}, {"assetId": "bin_20", "id": "GarbageCan|6|2", "kinematic": false, "position": {"x": 0.2892253041267395, "y": 0.32977062463760376, "z": 6.278964913343728}, "rotation": {"x": 0, "y": 90, "z": 0}, "layer": "Procedural1", "material": null}, {"assetId": "GarbageBag_21_2", "id": "GarbageBag|6|3", "kinematic": false, "position": {"x": 1.7785611838527995, "y": 0.2789691686630249, "z": 6.451719065546173}, "rotation": {"x": 0, "y": 270, "z": 0}, "layer": "Procedural1", "material": null}, {"assetId": "TV_Stand_204_1", "children": [{"assetId": "Television_1", "id": "Television|7|0|2", "kinematic": true, "position": {"x": 6.15590544128418, "y": 1.0657650232315063, "z": 4.187410660028457}, "rotation": {"x": 0, "y": 0.0, "z": 0}, "layer": "Procedural1"}, {"assetId": "CreditCard_2", "id": "CreditCard|surface|7|24", "kinematic": false, "position": {"x": 5.850504398345947, "y": 0.6982792019844055, "z": 4.5285115242004395}, "rotation": {"x": -0.0, "y": 89.99998474121094, "z": -0.0}, "layer": "Procedural1"}, {"assetId": "Remote_3", "id": "RemoteControl|surface|7|25", "kinematic": false, "position": {"x": 6.61187744140625, "y": 0.7067959308624268, "z": 4.415266990661621}, "rotation": {"x": -0.0, "y": 89.99998474121094, "z": -0.0}, "layer": "Procedural1"}], "id": "TVStand|7|0|0", "kinematic": true, "position": {"x": 6.15590544128418, "y": 0.3446730971336365, "z": 4.187410660028457}, "rotation": {"x": 0, "y": 0.0, "z": 0}, "layer": "Procedural1", "material": null}, {"assetId": "Sofa_215_1", "children": [{"assetId": "Book_21", "id": "Book|surface|7|26", "kinematic": false, "position": {"x": 6.7648162841796875, "y": 0.4633892774581909, "z": 7.119963645935059}, "rotation": {"x": -0.0, "y": 90.0000228881836, "z": -0.0}, "layer": "Procedural1"}, {"assetId": "pillow_24", "id": "Pillow|surface|7|28", "kinematic": false, "position": {"x": 5.851628303527832, "y": 0.5040515661239624, "z": 7.119518756866455}, "rotation": {"x": -0.0, "y": 90.0000228881836, "z": -0.0}, "layer": "Procedural1"}], "id": "Sofa|7|0|1", "kinematic": true, "position": {"x": 6.15590544128418, "y": 0.5669702291488647, "z": 7.29695731306076}, "rotation": {"x": 0, "y": 180.0, "z": 0}, "layer": "Procedural1", "material": null}, {"assetId": "Side_Table_205_2_1", "children": [{"assetId": "Vase_Flat_3", "color": {"b": 0.024174175949973287, "g": 0.0956549925698349, "r": 0.1738133491537519}, "id": "Vase|surface|7|19", "kinematic": false, "position": {"x": 4.423288345336914, "y": 0.9302050948143006, "z": 3.8832473754882812}, "rotation": {"x": -0.0, "y": 0.0, "z": 0.0}, "layer": "Procedural1"}, {"assetId": "RoboTHOR_candle_glittrig_3_v", "id": "Candle|surface|7|21", "kinematic": false, "position": {"x": 4.621232986450195, "y": 1.0346946716308594, "z": 4.083920478820801}, "rotation": {"x": -0.0, "y": 0.0, "z": 0.0}, "layer": "Procedural1"}, {"assetId": "Pen_3", "id": "Pen|surface|7|22", "kinematic": false, "position": {"x": 4.423287391662598, "y": 0.8507665395736694, "z": 4.157375335693359}, "rotation": {"x": -0.0, "y": 0.0, "z": 0.0}, "layer": "Procedural1"}, {"assetId": "Remote_3", "id": "RemoteControl|surface|7|27", "kinematic": false, "position": {"x": 4.61910343170166, "y": 0.8536720871925354, "z": 3.816021680831909}, "rotation": {"x": -0.0, "y": 90.0, "z": -0.0}, "layer": "Procedural1"}, {"assetId": "Cellphone_4", "id": "CellPhone|surface|7|29", "kinematic": false, "position": {"x": 4.622013092041016, "y": 0.898020613193512, "z": 3.9499709606170654}, "rotation": {"x": -0.0, "y": 90.0, "z": -0.0}, "layer": "Procedural1"}], "id": "SideTable|7|1", "kinematic": true, "position": {"x": 4.489270648738152, "y": 0.42006340622901917, "z": 4.016946799993515}, "rotation": {"x": 0, "y": 0, "z": 0}, "layer": "Procedural1", "material": null}, {"assetId": "Dining_Table_21_1", "children": [{"assetId": "Laptop_18", "id": "Laptop|surface|7|18", "kinematic": false, "openness": 0, "position": {"x": 7.058781623840332, "y": 0.7982304573059082, "z": 8.713520050048828}, "rotation": {"x": -0.0, "y": -8.196226553991437e-05, "z": 0.0}, "layer": "Procedural1"}, {"assetId": "RoboTHOR_candle_glittrig_2_v", "id": "Candle|surface|7|23", "kinematic": false, "position": {"x": 7.058781147003174, "y": 0.8919329643249512, "z": 9.03863525390625}, "rotation": {"x": -0.0, "y": -8.196226553991437e-05, "z": 0.0}, "layer": "Procedural1"}, {"assetId": "RoboTHOR_pen_signo_v", "id": "Pen|surface|7|30", "kinematic": false, "position": {"x": 7.061826229095459, "y": 0.7346138954162598, "z": 8.931135177612305}, "rotation": {"x": -0.0, "y": 89.99993133544922, "z": 0.0}, "layer": "Procedural1"}], "id": "DiningTable|7|2", "kinematic": true, "position": {"x": 7.059967473983765, "y": 0.360828161239624, "z": 8.82814329123497}, "rotation": {"x": 0, "y": 270, "z": 0}, "layer": "Procedural1", "material": null}, {"assetId": "bin_6", "children": [{"assetId": "Candle_5", "id": "Candle|surface|7|20", "kinematic": false, "position": {"x": 4.404725074768066, "y": 0.23173898458480835, "z": 9.131542205810547}, "rotation": {"x": 0.00020981489797122777, "y": 180.0, "z": 0.00010223682329524308}, "layer": "Procedural1"}], "id": "GarbageCan|7|3", "kinematic": false, "position": {"x": 4.487461254134427, "y": 0.2730902433395386, "z": 9.102929242014884}, "rotation": {"x": 0, "y": 180, "z": 0}, "layer": "Procedural1", "material": null}, {"assetId": "Bed_8", "children": [{"assetId": "pillow_4", "id": "Pillow|2|0|2", "kinematic": false, "position": {"x": 6.773988697767258, "y": 0.9482516199350357, "z": 0.45709001421928397}, "rotation": {"x": 0, "y": 0.0, "z": 0}, "layer": "Procedural2"}, {"assetId": "pillow_4", "id": "Pillow|2|0|1", "kinematic": false, "position": {"x": 6.24575906777382, "y": 0.9482516199350357, "z": 0.45709001421928397}, "rotation": {"x": 0, "y": 0.0, "z": 0}, "layer": "Procedural2"}, {"assetId": "Book_27", "id": "Book|surface|2|43", "kinematic": false, "position": {"x": 6.693645477294922, "y": 0.7929751873016357, "z": 1.811727523803711}, "rotation": {"x": -0.0, "y": 0.0, "z": 0.0}, "layer": "Procedural2"}, {"assetId": "Remote_2", "id": "RemoteControl|surface|2|44", "kinematic": false, "position": {"x": 7.099447250366211, "y": 0.7913363575935364, "z": 0.6539928913116455}, "rotation": {"x": -0.0, "y": 0.0, "z": 0.0}, "layer": "Procedural2"}, {"assetId": "Alarm_Clock_21", "id": "AlarmClock|surface|2|45", "kinematic": false, "position": {"x": 6.085053443908691, "y": 0.8611564636230469, "z": 0.9375137090682983}, "rotation": {"x": -0.0, "y": 0.0, "z": 0.0}, "layer": "Procedural2"}, {"assetId": "BaseballBat_4", "id": "BaseballBat|surface|2|48", "kinematic": false, "position": {"x": 6.833049297332764, "y": 0.8278043866157532, "z": 0.805705189704895}, "rotation": {"x": 359.91009521484375, "y": 199.2501983642578, "z": 88.44844055175781}, "layer": "Procedural2"}], "id": "Bed|2|0|0", "isDirty": true, "kinematic": true, "position": {"x": 6.509873882770538, "y": 0.447925329208374, "z": 1.2402013778686523}, "rotation": {"x": 0, "y": 0.0, "z": 0}, "layer": "Procedural2", "material": null}, {"assetId": "Dresser_217_1", "children": [{"assetId": "Tissue_Box_1", "id": "TissueBox|surface|2|31", "kinematic": false, "position": {"x": 0.1999116986989975, "y": 1.0610593557357788, "z": 1.1687536239624023}, "rotation": {"x": -0.0, "y": 2.390565896348562e-05, "z": -0.0}, "layer": "Procedural2"}, {"assetId": "RoboTHOR_mug_ai2_1_v", "id": "Mug|surface|2|32", "kinematic": false, "position": {"x": 0.5194399356842041, "y": 0.2266959398984909, "z": 0.3891364336013794}, "rotation": {"x": -0.0, "y": 2.390565896348562e-05, "z": -0.0}, "layer": "Procedural2"}, {"assetId": "Bowl_10", "id": "Bowl|surface|2|34", "kinematic": false, "position": {"x": 0.47508108615875244, "y": 0.2197616696357727, "z": 1.0350823402404785}, "rotation": {"x": -0.0, "y": 2.390565896348562e-05, "z": -0.0}, "layer": "Procedural2"}, {"assetId": "Watch_2", "id": "Watch|surface|2|39", "kinematic": false, "position": {"x": 0.5719313621520996, "y": 0.9045460224151611, "z": 1.8931400775909424}, "rotation": {"x": -0.0, "y": 2.390565896348562e-05, "z": -0.0}, "layer": "Procedural2"}, {"assetId": "Stone_Statue_4", "color": {"b": 0.3787429385362149, "g": 0.7561843972731835, "r": 0.46031433394085874}, "id": "Statue|surface|2|42", "kinematic": false, "position": {"x": 0.19206443428993225, "y": 1.3289558172225953, "z": 0.6003689765930176}, "rotation": {"x": -0.0, "y": 2.390565896348562e-05, "z": -0.0}, "layer": "Procedural2"}, {"assetId": "Desk_Lamp_11", "id": "DeskLamp|surface|2|46", "isOn": false, "kinematic": false, "position": {"x": 0.4625564515590668, "y": 1.2376039028167725, "z": 2.0213305950164795}, "rotation": {"x": -0.0, "y": 2.390565896348562e-05, "z": -0.0}, "layer": "Procedural2"}], "id": "Dresser|2|1", "kinematic": true, "position": {"x": 0.37500479221343996, "y": 0.49052125215530396, "z": 1.1687537670135497}, "rotation": {"x": 0, "y": 90, "z": 0}, "layer": "Procedural2", "material": null}, {"assetId": "Armchair_219_1", "id": "ArmChair|2|2|0", "kinematic": true, "position": {"x": 4.383644214861352, "y": 0.6352773904800415, "z": 0.5178540587425232}, "rotation": {"x": 0, "y": 0.0, "z": 0}, "layer": "Procedural2", "material": null}, {"assetId": "Floor_Lamp_18", "id": "FloorLamp|2|2|1", "isOn": false, "kinematic": false, "position": {"x": 3.159296694087529, "y": 0.9146366119384766, "z": 0.5178540587425232}, "rotation": {"x": 0, "y": 27.868389374961737, "z": 0}, "layer": "Procedural2", "material": null}, {"assetId": "Armchair_222_1", "id": "ArmChair|2|3|0", "kinematic": true, "position": {"x": 2.8635289583272625, "y": 0.47257378697395325, "z": 3.201443482875824}, "rotation": {"x": 0, "y": 180.0, "z": 0}, "layer": "Procedural2", "material": null}, {"assetId": "Floor_Lamp_5", "id": "FloorLamp|2|3|1", "isOn": true, "kinematic": false, "position": {"x": 3.8842990149012095, "y": 0.9235444664955139, "z": 3.201443482875824}, "rotation": {"x": 0, "y": 67.35445249736303, "z": 0}, "layer": "Procedural2", "material": null}, {"assetId": "Houseplant_6", "id": "HousePlant|2|4|0", "kinematic": false, "position": {"x": 2.3100732559084713, "y": 0.4925673007965088, "z": 0.38838061104928057}, "rotation": {"x": 0, "y": 74.49909879754918, "z": 0}, "layer": "Procedural2", "material": null}, {"assetId": "Desk_308_1_1", "children": [{"assetId": "Keychain_2", "id": "KeyChain|surface|2|33", "kinematic": false, "position": {"x": 5.292132377624512, "y": 0.09633810818195343, "z": 3.269421100616455}, "rotation": {"x": 0.0, "y": 180.0, "z": 0.0}, "layer": "Procedural2"}, {"assetId": "Tabletop_Decor_1_1", "id": "TableTopDecor|surface|2|35", "kinematic": false, "position": {"x": 5.194777011871338, "y": 1.7973549365997314, "z": 3.4988961219787598}, "rotation": {"x": 0.0, "y": 180.0, "z": 0.0}, "layer": "Procedural2"}, {"assetId": "Book_27", "id": "Book|surface|2|36", "kinematic": false, "position": {"x": 4.879822254180908, "y": 0.8992346525192261, "z": 3.498851776123047}, "rotation": {"x": 0.0, "y": 270.0, "z": 0.0}, "layer": "Procedural2"}, {"assetId": "Book_4", "id": "Book|surface|2|37", "kinematic": false, "position": {"x": 5.404326438903809, "y": 0.895569920539856, "z": 3.4581332206726074}, "rotation": {"x": 0.0, "y": 180.0, "z": 0.0}, "layer": "Procedural2"}, {"assetId": "CreditCard_2", "id": "CreditCard|surface|2|38", "kinematic": false, "position": {"x": 4.774837493896484, "y": 1.7304941415786743, "z": 3.4586331844329834}, "rotation": {"x": 0.0, "y": 180.0, "z": 0.0}, "layer": "Procedural2"}, {"assetId": "Pencil_3", "id": "Pencil|surface|2|40", "kinematic": false, "position": {"x": 5.374207973480225, "y": 0.8671125173568726, "z": 3.205561876296997}, "rotation": {"x": 0.0, "y": 180.0, "z": 0.0}, "layer": "Procedural2"}, {"assetId": "Remote_1", "id": "RemoteControl|surface|2|41", "kinematic": false, "position": {"x": 4.428110122680664, "y": 0.8934128284454346, "z": 3.619685173034668}, "rotation": {"x": 0.0, "y": 270.0, "z": 0.0}, "layer": "Procedural2"}, {"assetId": "Cellphone_4", "id": "CellPhone|surface|2|47", "kinematic": false, "position": {"x": 4.940756320953369, "y": 0.7114656448364258, "z": 3.1864075660705566}, "rotation": {"x": 0.0, "y": 180.0, "z": 0.0}, "layer": "Procedural2"}], "id": "Desk|2|5", "kinematic": true, "position": {"x": 4.852565960934621, "y": 1.0385403633117676, "z": 3.343068410396576}, "rotation": {"x": 0, "y": 180, "z": 0}, "layer": "Procedural2", "material": null}, {"assetId": "Television_3", "id": "Television|6|4", "kinematic": true, "position": {"x": 0.04345352679491043, "y": 1.512195770983164, "z": 4.801523402967356}, "rotation": {"x": 0, "y": 90, "z": 0}, "layer": "Procedural1", "material": null}, {"assetId": "Wall_Decor_Photo_2", "id": "Painting|2|6", "kinematic": true, "position": {"x": 1.822485475239245, "y": 2.055798210857444, "z": 0.020870485454797746}, "rotation": {"x": 0, "y": 0, "z": 0}, "layer": "Procedural2", "material": null}, {"assetId": "Wall_Decor_Photo_1V", "id": "Painting|2|7", "kinematic": true, "position": {"x": 2.011971114228839, "y": 1.0937749052393255, "z": 3.6931295145452023}, "rotation": {"x": 0, "y": 180, "z": 0}, "layer": "Procedural2", "material": null}, {"assetId": "Wall_Decor_Painting_10", "id": "Painting|6|5", "kinematic": true, "position": {"x": 2.355407182780385, "y": 1.3211552623068759, "z": 9.273000348865985}, "rotation": {"x": 0, "y": 180, "z": 0}, "layer": "Procedural1", "material": null}, {"assetId": "Wall_Decor_Painting_6", "id": "Painting|6|6", "kinematic": true, "position": {"x": 0.02135, "y": 1.676637788103572, "z": 6.301784085258065}, "rotation": {"x": 0, "y": 90, "z": 0}, "layer": "Procedural1", "material": null}, {"assetId": "Wall_Decor_Painting_8", "id": "Painting|6|7", "kinematic": true, "position": {"x": 0.013605435490608216, "y": 1.555081118997164, "z": 10.598602140615748}, "rotation": {"x": 0, "y": 90, "z": 0}, "layer": "Procedural1", "material": null}, {"assetId": "Wall_Decor_Painting_3V", "id": "Painting|6|8", "kinematic": true, "position": {"x": 3.1553462789518427, "y": 1.5431979012188233, "z": 9.265129514545201}, "rotation": {"x": 0, "y": 180, "z": 0}, "layer": "Procedural1", "material": null}, {"assetId": "Wall_Decor_Painting_1V", "id": "Painting|7|4", "kinematic": true, "position": {"x": 7.408129514545203, "y": 1.914258560031688, "z": 8.787831399684059}, "rotation": {"x": 0, "y": 270, "z": 0}, "layer": "Procedural1", "material": null}, {"assetId": "Wall_Decor_Photo_1", "id": "Painting|7|5", "kinematic": true, "position": {"x": 4.532342973611959, "y": 1.813768208727634, "z": 3.7348704854547976}, "rotation": {"x": 0, "y": 0, "z": 0}, "layer": "Procedural1", "material": null}], "proceduralParameters": {"ceilingColor": {"b": 0.9176470588235294, "g": 0.9411764705882353, "r": 0.9490196078431372}, "ceilingMaterial": {"name": "PureWhite", "color": {"b": 0.9176470588235294, "g": 0.9411764705882353, "r": 0.9490196078431372}}, "floorColliderThickness": 1.0, "lights": [{"id": "DirectionalLight", "indirectMultiplier": 1.0, "intensity": 1, "position": {"x": 0.84, "y": 0.1855, "z": -1.09}, "rgb": {"r": 1.0, "g": 1.0, "b": 1.0}, "rotation": {"x": 66, "y": 75, "z": 0}, "shadow": {"type": "Soft", "strength": 1, "normalBias": 0, "bias": 0, "nearPlane": 0.2, "resolution": "FromQualitySettings"}, "type": "directional"}, {"id": "light_2", "intensity": 0.45, "position": {"x": 3.7145, "y": 2.6257532567041926, "z": 1.857}, "range": 15, "rgb": {"r": 1.0, "g": 0.855, "b": 0.722}, "shadow": {"type": "Soft", "strength": 1, "normalBias": 0, "bias": 0.05, "nearPlane": 0.2, "resolution": "FromQualitySettings"}, "type": "point", "layer": "Procedural2", "cullingMaskOff": ["Procedural0", "Procedural1", "Procedural3"]}, {"id": "light_6", "intensity": 0.45, "position": {"x": 1.7243775478809322, "y": 2.6257532567041926, "z": 7.030561226059534}, "range": 15, "rgb": {"r": 1.0, "g": 0.855, "b": 0.722}, "shadow": {"type": "Soft", "strength": 1, "normalBias": 0, "bias": 0.05, "nearPlane": 0.2, "resolution": "FromQualitySettings"}, "type": "point", "layer": "Procedural1", "cullingMaskOff": ["Procedural0", "Procedural2", "Procedural3"]}, {"id": "light_7", "intensity": 0.45, "position": {"x": 5.5715, "y": 2.6257532567041926, "z": 6.5}, "range": 15, "rgb": {"r": 1.0, "g": 0.855, "b": 0.722}, "shadow": {"type": "Soft", "strength": 1, "normalBias": 0, "bias": 0.05, "nearPlane": 0.2, "resolution": "FromQualitySettings"}, "type": "point", "layer": "Procedural1", "cullingMaskOff": ["Procedural0", "Procedural2", "Procedural3"]}], "receptacleHeight": 0.7, "reflections": [], "skyboxId": "Sky2"}, "rooms": [{"ceilings": [], "children": [], "floorMaterial": {"name": "DarkWoodPlanks"}, "floorPolygon": [{"x": 7.429, "y": 0, "z": 0.0}, {"x": 0.0, "y": 0, "z": 0.0}, {"x": 0.0, "y": 0, "z": 3.714}, {"x": 3.714, "y": 0, "z": 3.714}, {"x": 7.429, "y": 0, "z": 3.714}], "id": "room|2", "roomType": "Bedroom", "layer": "Procedural2"}, {"ceilings": [], "children": [], "floorMaterial": {"name": "DarkWoodFloors"}, "floorPolygon": [{"x": 1.857, "y": 0, "z": 9.286}, {"x": 3.714, "y": 0, "z": 9.286}, {"x": 3.714, "y": 0, "z": 3.714}, {"x": 0.0, "y": 0, "z": 3.714}, {"x": 0.0, "y": 0, "z": 11.143}, {"x": 1.857, "y": 0, "z": 11.143}], "id": "room|6", "roomType": "Kitchen", "layer": "Procedural1"}, {"ceilings": [], "children": [], "floorMaterial": {"name": "TexturesCom_WoodFine0044_1_seamless_S"}, "floorPolygon": [{"x": 3.714, "y": 0, "z": 3.714}, {"x": 3.714, "y": 0, "z": 9.286}, {"x": 7.429, "y": 0, "z": 9.286}, {"x": 7.429, "y": 0, "z": 3.714}], "id": "room|7", "roomType": "LivingRoom", "layer": "Procedural1"}], "walls": [{"color": {"b": 0.9058823529411765, "g": 0.9254901960784314, "r": 0.8627450980392157}, "id": "wall|2|0.00|0.00|7.43|0.00", "material": {"name": "PureWhite", "color": {"b": 0.9058823529411765, "g": 0.9254901960784314, "r": 0.8627450980392157}}, "polygon": [{"x": 7.429, "y": 0, "z": 0.0}, {"x": 0.0, "y": 0, "z": 0.0}, {"x": 7.429, "y": 2.8257532567041928, "z": 0.0}, {"x": 0.0, "y": 2.8257532567041928, "z": 0.0}], "roomId": "room|2", "layer": "Procedural2"}, {"color": {"b": 0.9058823529411765, "g": 0.9254901960784314, "r": 0.8627450980392157}, "id": "wall|2|0.00|0.00|0.00|3.71", "material": {"name": "PureWhite", "color": {"b": 0.9058823529411765, "g": 0.9254901960784314, "r": 0.8627450980392157}}, "polygon": [{"x": 0.0, "y": 0, "z": 0.0}, {"x": 0.0, "y": 0, "z": 3.714}, {"x": 0.0, "y": 2.8257532567041928, "z": 0.0}, {"x": 0.0, "y": 2.8257532567041928, "z": 3.714}], "roomId": "room|2", "layer": "Procedural2"}, {"color": {"b": 0.9058823529411765, "g": 0.9254901960784314, "r": 0.8627450980392157}, "id": "wall|2|0.00|3.71|3.71|3.71", "material": {"name": "PureWhite", "color": {"b": 0.9058823529411765, "g": 0.9254901960784314, "r": 0.8627450980392157}}, "polygon": [{"x": 0.0, "y": 0, "z": 3.714}, {"x": 3.714, "y": 0, "z": 3.714}, {"x": 0.0, "y": 2.8257532567041928, "z": 3.714}, {"x": 3.714, "y": 2.8257532567041928, "z": 3.714}], "roomId": "room|2", "layer": "Procedural2"}, {"color": {"b": 0.9058823529411765, "g": 0.9254901960784314, "r": 0.8627450980392157}, "id": "wall|2|3.71|3.71|7.43|3.71", "material": {"name": "PureWhite", "color": {"b": 0.9058823529411765, "g": 0.9254901960784314, "r": 0.8627450980392157}}, "polygon": [{"x": 3.714, "y": 0, "z": 3.714}, {"x": 7.429, "y": 0, "z": 3.714}, {"x": 3.714, "y": 2.8257532567041928, "z": 3.714}, {"x": 7.429, "y": 2.8257532567041928, "z": 3.714}], "roomId": "room|2", "layer": "Procedural2"}, {"color": {"b": 0.9058823529411765, "g": 0.9254901960784314, "r": 0.8627450980392157}, "id": "wall|2|7.43|0.00|7.43|3.71", "material": {"name": "PureWhite", "color": {"b": 0.9058823529411765, "g": 0.9254901960784314, "r": 0.8627450980392157}}, "polygon": [{"x": 7.429, "y": 0, "z": 3.714}, {"x": 7.429, "y": 0, "z": 0.0}, {"x": 7.429, "y": 2.8257532567041928, "z": 3.714}, {"x": 7.429, "y": 2.8257532567041928, "z": 0.0}], "roomId": "room|2", "layer": "Procedural2"}, {"id": "wall|6|1.86|9.29|3.71|9.29", "material": {"name": "KitchenTiles4"}, "polygon": [{"x": 1.857, "y": 0, "z": 9.286}, {"x": 3.714, "y": 0, "z": 9.286}, {"x": 1.857, "y": 2.8257532567041928, "z": 9.286}, {"x": 3.714, "y": 2.8257532567041928, "z": 9.286}], "roomId": "room|6", "layer": "Procedural1"}, {"empty": true, "id": "wall|6|3.71|3.71|3.71|9.29", "material": {"name": "KitchenTiles4"}, "polygon": [{"x": 3.714, "y": 0, "z": 9.286}, {"x": 3.714, "y": 0, "z": 3.714}, {"x": 3.714, "y": 2.8257532567041928, "z": 9.286}, {"x": 3.714, "y": 2.8257532567041928, "z": 3.714}], "roomId": "room|6", "layer": "Procedural1"}, {"id": "wall|6|0.00|3.71|3.71|3.71", "material": {"name": "KitchenTiles4"}, "polygon": [{"x": 3.714, "y": 0, "z": 3.714}, {"x": 0.0, "y": 0, "z": 3.714}, {"x": 3.714, "y": 2.8257532567041928, "z": 3.714}, {"x": 0.0, "y": 2.8257532567041928, "z": 3.714}], "roomId": "room|6", "layer": "Procedural1"}, {"id": "wall|6|0.00|3.71|0.00|11.14", "material": {"name": "KitchenTiles4"}, "polygon": [{"x": 0.0, "y": 0, "z": 3.714}, {"x": 0.0, "y": 0, "z": 11.143}, {"x": 0.0, "y": 2.8257532567041928, "z": 3.714}, {"x": 0.0, "y": 2.8257532567041928, "z": 11.143}], "roomId": "room|6", "layer": "Procedural1"}, {"id": "wall|6|0.00|11.14|1.86|11.14", "material": {"name": "KitchenTiles4"}, "polygon": [{"x": 0.0, "y": 0, "z": 11.143}, {"x": 1.857, "y": 0, "z": 11.143}, {"x": 0.0, "y": 2.8257532567041928, "z": 11.143}, {"x": 1.857, "y": 2.8257532567041928, "z": 11.143}], "roomId": "room|6", "layer": "Procedural1"}, {"id": "wall|6|1.86|9.29|1.86|11.14", "material": {"name": "KitchenTiles4"}, "polygon": [{"x": 1.857, "y": 0, "z": 11.143}, {"x": 1.857, "y": 0, "z": 9.286}, {"x": 1.857, "y": 2.8257532567041928, "z": 11.143}, {"x": 1.857, "y": 2.8257532567041928, "z": 9.286}], "roomId": "room|6", "layer": "Procedural1"}, {"color": {"b": 0.25098039215686274, "g": 0.25098039215686274, "r": 0.2549019607843137}, "empty": true, "id": "wall|7|3.71|3.71|3.71|9.29", "material": {"name": "PureWhite", "color": {"b": 0.25098039215686274, "g": 0.25098039215686274, "r": 0.2549019607843137}}, "polygon": [{"x": 3.714, "y": 0, "z": 3.714}, {"x": 3.714, "y": 0, "z": 9.286}, {"x": 3.714, "y": 2.8257532567041928, "z": 3.714}, {"x": 3.714, "y": 2.8257532567041928, "z": 9.286}], "roomId": "room|7", "layer": "Procedural1"}, {"color": {"b": 0.25098039215686274, "g": 0.25098039215686274, "r": 0.2549019607843137}, "id": "wall|7|3.71|9.29|7.43|9.29", "material": {"name": "PureWhite", "color": {"b": 0.25098039215686274, "g": 0.25098039215686274, "r": 0.2549019607843137}}, "polygon": [{"x": 3.714, "y": 0, "z": 9.286}, {"x": 7.429, "y": 0, "z": 9.286}, {"x": 3.714, "y": 2.8257532567041928, "z": 9.286}, {"x": 7.429, "y": 2.8257532567041928, "z": 9.286}], "roomId": "room|7", "layer": "Procedural1"}, {"color": {"b": 0.25098039215686274, "g": 0.25098039215686274, "r": 0.2549019607843137}, "id": "wall|7|7.43|3.71|7.43|9.29", "material": {"name": "PureWhite", "color": {"b": 0.25098039215686274, "g": 0.25098039215686274, "r": 0.2549019607843137}}, "polygon": [{"x": 7.429, "y": 0, "z": 9.286}, {"x": 7.429, "y": 0, "z": 3.714}, {"x": 7.429, "y": 2.8257532567041928, "z": 9.286}, {"x": 7.429, "y": 2.8257532567041928, "z": 3.714}], "roomId": "room|7", "layer": "Procedural1"}, {"color": {"b": 0.25098039215686274, "g": 0.25098039215686274, "r": 0.2549019607843137}, "id": "wall|7|3.71|3.71|7.43|3.71", "material": {"name": "PureWhite", "color": {"b": 0.25098039215686274, "g": 0.25098039215686274, "r": 0.2549019607843137}}, "polygon": [{"x": 7.429, "y": 0, "z": 3.714}, {"x": 3.714, "y": 0, "z": 3.714}, {"x": 7.429, "y": 2.8257532567041928, "z": 3.714}, {"x": 3.714, "y": 2.8257532567041928, "z": 3.714}], "roomId": "room|7", "layer": "Procedural1"}, {"id": "wall|exterior|7.43|0.00|7.43|3.71", "material": {"name": "bathroomTilesBlue"}, "polygon": [{"x": 7.429, "y": 2.8257532567041928, "z": 0.0}, {"x": 7.429, "y": 2.8257532567041928, "z": 3.714}, {"x": 7.429, "y": 0, "z": 0.0}, {"x": 7.429, "y": 0, "z": 3.714}], "roomId": "exterior", "layer": "Procedural2"}, {"id": "wall|exterior|0.00|0.00|7.43|0.00", "material": {"name": "bathroomTilesBlue"}, "polygon": [{"x": 0.0, "y": 2.8257532567041928, "z": 0.0}, {"x": 7.429, "y": 2.8257532567041928, "z": 0.0}, {"x": 0.0, "y": 0, "z": 0.0}, {"x": 7.429, "y": 0, "z": 0.0}], "roomId": "exterior", "layer": "Procedural2"}, {"id": "wall|exterior|0.00|0.00|0.00|3.71", "material": {"name": "bathroomTilesBlue"}, "polygon": [{"x": 0.0, "y": 2.8257532567041928, "z": 3.714}, {"x": 0.0, "y": 2.8257532567041928, "z": 0.0}, {"x": 0.0, "y": 0, "z": 3.714}, {"x": 0.0, "y": 0, "z": 0.0}], "roomId": "exterior", "layer": "Procedural2"}, {"id": "wall|exterior|1.86|9.29|3.71|9.29", "material": {"name": "bathroomTilesBlue"}, "polygon": [{"x": 3.714, "y": 2.8257532567041928, "z": 9.286}, {"x": 1.857, "y": 2.8257532567041928, "z": 9.286}, {"x": 3.714, "y": 0, "z": 9.286}, {"x": 1.857, "y": 0, "z": 9.286}], "roomId": "exterior", "layer": "Procedural1"}, {"id": "wall|exterior|0.00|11.14|1.86|11.14", "material": {"name": "bathroomTilesBlue"}, "polygon": [{"x": 1.857, "y": 2.8257532567041928, "z": 11.143}, {"x": 0.0, "y": 2.8257532567041928, "z": 11.143}, {"x": 1.857, "y": 0, "z": 11.143}, {"x": 0.0, "y": 0, "z": 11.143}], "roomId": "exterior", "layer": "Procedural1"}, {"id": "wall|exterior|0.00|3.71|0.00|11.14", "material": {"name": "bathroomTilesBlue"}, "polygon": [{"x": 0.0, "y": 2.8257532567041928, "z": 11.143}, {"x": 0.0, "y": 2.8257532567041928, "z": 3.714}, {"x": 0.0, "y": 0, "z": 11.143}, {"x": 0.0, "y": 0, "z": 3.714}], "roomId": "exterior", "layer": "Procedural1"}, {"id": "wall|exterior|1.86|9.29|1.86|11.14", "material": {"name": "bathroomTilesBlue"}, "polygon": [{"x": 1.857, "y": 2.8257532567041928, "z": 9.286}, {"x": 1.857, "y": 2.8257532567041928, "z": 11.143}, {"x": 1.857, "y": 0, "z": 9.286}, {"x": 1.857, "y": 0, "z": 11.143}], "roomId": "exterior", "layer": "Procedural1"}, {"id": "wall|exterior|3.71|9.29|7.43|9.29", "material": {"name": "bathroomTilesBlue"}, "polygon": [{"x": 7.429, "y": 2.8257532567041928, "z": 9.286}, {"x": 3.714, "y": 2.8257532567041928, "z": 9.286}, {"x": 7.429, "y": 0, "z": 9.286}, {"x": 3.714, "y": 0, "z": 9.286}], "roomId": "exterior", "layer": "Procedural1"}, {"id": "wall|exterior|7.43|3.71|7.43|9.29", "material": {"name": "bathroomTilesBlue"}, "polygon": [{"x": 7.429, "y": 2.8257532567041928, "z": 3.714}, {"x": 7.429, "y": 2.8257532567041928, "z": 9.286}, {"x": 7.429, "y": 0, "z": 3.714}, {"x": 7.429, "y": 0, "z": 9.286}], "roomId": "exterior", "layer": "Procedural1"}], "windows": [{"assetId": "Window_Slider_48x48", "id": "window|2|0", "room0": "room|2", "room1": "room|2", "wall0": "wall|2|0.00|0.00|0.00|3.71", "wall1": "wall|exterior|0.00|0.00|0.00|3.71", "holePolygon": [{"x": 2.454095208470806, "y": 0.8021997437009123, "z": 0}, {"x": 3.67033907157658, "y": 2.0156241580971983, "z": 0}], "assetPosition": {"x": 3.0631975768256035, "y": 1.410853676510742, "z": 0}}, {"assetId": "Window_Hung_48x32", "id": "window|6|0", "room0": "room|6", "room1": "room|6", "wall0": "wall|6|0.00|3.71|0.00|11.14", "wall1": "wall|exterior|0.00|3.71|0.00|11.14", "holePolygon": [{"x": 3.2755974316217134, "y": 0.9766211733350065, "z": 0}, {"x": 4.490968682727976, "y": 1.8428308591374662, "z": 0}], "assetPosition": {"x": 3.884271972737474, "y": 1.4128766283520964, "z": 0}}, {"assetId": "Window_Hung_44x60", "id": "window|6|1", "room0": "room|6", "room1": "room|6", "wall0": "wall|6|1.86|9.29|1.86|11.14", "wall1": "wall|exterior|1.86|9.29|1.86|11.14", "holePolygon": [{"x": 0.36675644266454577, "y": 0.6217507347592619, "z": 0}, {"x": 1.4812794958337963, "y": 2.1984146461018828, "z": 0}], "assetPosition": {"x": 0.9289734966606319, "y": 1.412195526076248, "z": 0}}, {"assetId": "Window_Slider_48x36", "id": "window|7|0", "room0": "room|7", "room1": "room|7", "wall0": "wall|7|3.71|9.29|7.43|9.29", "wall1": "wall|exterior|3.71|9.29|7.43|9.29", "holePolygon": [{"x": 1.1143746567259463, "y": 0.955676697207382, "z": 0}, {"x": 2.3283654642592104, "y": 1.8673416674265173, "z": 0}], "assetPosition": {"x": 1.7239822638521822, "y": 1.410236671579769, "z": 0}}]}